{
  "by_name": {
    "W01L1 - Alle kilder [EN].mp3": {
      "relative_path": "W01L1/W01L1 - Alle kilder [EN].html",
      "format": "html"
    },
    "W01L1 - Grundbog kapitel 01 - Introduktion til personlighedspsykologi [EN].mp3": {
      "relative_path": "W01L1/W01L1 - W01L1 Grundbog kapitel 01 - Introduktion til personlighedspsykologi [EN].html",
      "format": "html"
    },
    "W01L1 - Lewis (1999) [EN].mp3": {
      "relative_path": "W01L1/W01L1 - W01L1 Lewis (1999) [EN].html",
      "format": "html"
    },
    "W01L2 - Alle kilder [EN].mp3": {
      "relative_path": "W01L2/W01L2 - Alle kilder [EN].html",
      "format": "html"
    },
    "W01L2 - Koutsoumpis (2025) [EN].mp3": {
      "relative_path": "W01L2/W01L2 - W01L2 Koutsoumpis (2025) [EN].html",
      "format": "html"
    },
    "W01L2 - Mayer & Bryan (2024) [EN].mp3": {
      "relative_path": "W01L2/W01L2 - W01L2 Mayer & Bryan (2024) [EN].html",
      "format": "html"
    },
    "W01L2 - Phan et al. (2024) [EN].mp3": {
      "relative_path": "W01L2/W01L2 - W01L2 Phan et al..... (2024) [EN].html",
      "format": "html"
    },
    "W02L1 - Alle kilder [EN].mp3": {
      "relative_path": "W02L1/W02L1 - Alle kilder [EN].html",
      "format": "html"
    },
    "W02L1 - Columbus & Strandsbjerg (2025) [EN].mp3": {
      "relative_path": "W02L1/W02L1 - W02L1 Columbus & Strandsbjerg (2025) [EN].html",
      "format": "html"
    },
    "W02L1 X Zettler et al. (2020) [EN].mp3": {
      "relative_path": "W02L1/W02L1 - W02L1 X Zettler et al.... (2020) [EN].html",
      "format": "html"
    },
    "[Brief] W01L1 - Grundbog kapitel 01 - Introduktion til personlighedspsykologi [EN].mp3": {
      "relative_path": "W01L1/[Brief] W01L1 - W01L1 Grundbog kapitel 01 - Introduktion til personlighedspsykologi [EN].html",
      "format": "html"
    }
  }
}
